{
  "shoppingList": [
    {
      "id": 1 ,
      "name": "dupa ",
      "brand": "Almette",
      "price": 250,
      "calories": 200,
      "shop": "AUCHAN",
      "productCategory": "NABIAŁ",
      "amount": 1

    },
    {
      "id": 2 ,
      "name": "Mrożona mieszanka warzywna",
      "brand": "Hortex",
      "price": 400,
      "calories": 350,
      "shop": "TESCO",
      "productCategory": "WARZYWA",
      "amount": 1
    },
    {
      "id": 3 ,
      "name": "Mrożona mieszanka warzywna",
      "brand": "Hortex",
      "price": 400,
      "calories": 350,
      "shop": "TESCO",
      "productCategory": "WARZYWA",
      "amount": 1
    },
    {
      "id": 4 ,
      "name": "Ogórki po kaszubsku",
      "brand": "Tesco",
      "price": 549,
      "calories": 340,
      "shop": "TESCO",
      "productCategory": "WARZYWA",
      "amount": 1
    },
    {
      "id": 5 ,
      "name": "Jogurt Danone",
      "brand": "Danone",
      "price": 450,
      "calories": 69,
      "shop": "AUCHAN",
      "productCategory": "NABIAŁ",
      "amount": 1
    },
    {
      "id": 6 ,
      "name": "Pomarańcz",
      "brand": "Java",
      "price": 150,
      "calories": 50,
      "shop": "TESCO",
      "productCategory": "OWOCE",
      "amount": 1
    }
  ]
}
